sweep_design/__init__.py
sweep_design/axis.py
sweep_design/config/__init__.py
sweep_design/config/base_config.py
sweep_design/config/sweep_config.py
sweep_design/core.py
sweep_design/defaults/__init__.py
sweep_design/defaults/methods.py
sweep_design/defaults/sweep_methods.py
sweep_design/exc.py
sweep_design/help_types.py
sweep_design/prepared_sweeps/__init__.py
sweep_design/prepared_sweeps/code_m_sequence.py
sweep_design/prepared_sweeps/code_zinger.py
sweep_design/prepared_sweeps/dwell_sweep.py
sweep_design/prepared_sweeps/linear_sweep.py
sweep_design/prepared_sweeps/pseudorandom_shuffle.py
sweep_design/prepared_sweeps/sweep_from_code.py
sweep_design/relation.py
sweep_design/signal.py
sweep_design/spectrogram.py
sweep_design/spectrum.py
sweep_design/sweep.py
sweep_design/uncalculated_sweep.py
sweep_design/utility_functions/__init__.py
sweep_design/utility_functions/a_t.py
sweep_design/utility_functions/emd_analyze.py
sweep_design/utility_functions/f_t.py
sweep_design/utility_functions/ftat_functions.py
sweep_design/utility_functions/source_sweep_correction.py
sweep_design/utility_functions/sweep_correction.py
sweep_design-0.3.1.dist-info/LICENSE
sweep_design-0.3.1.dist-info/METADATA
sweep_design-0.3.1.dist-info/WHEEL
sweep_design-0.3.1.dist-info/RECORD
