Metadata-Version: 2.1
Name: sweep-design
Version: 0.3.1
Summary: Project designed to create and analyze sweep signals.
License: MIT
Author: Vladislav
Author-email: serebraykov.vs@gmail.com
Requires-Python: >=3.7,<4.0
Classifier: License :: OSI Approved :: MIT License
Classifier: Programming Language :: Python :: 3
Classifier: Programming Language :: Python :: 3.7
Classifier: Programming Language :: Python :: 3.8
Classifier: Programming Language :: Python :: 3.9
Classifier: Programming Language :: Python :: 3.10
Classifier: Programming Language :: Python :: 3.11
Requires-Dist: emd-signal (>=1.2.3,<2.0.0)
Requires-Dist: numpy (<=1.19) ; python_version >= "3.6" and python_version < "3.8"
Requires-Dist: numpy (>1.19) ; python_version >= "3.8"
Requires-Dist: packaging (>=22,<23)
Requires-Dist: scipy (>=1.2,<1.8) ; python_version >= "3.6" and python_version < "3.8"
Requires-Dist: scipy (>=1.8) ; python_version >= "3.8"
Requires-Dist: typing_extensions (>=3.6) ; python_version >= "3.6" and python_version < "3.8"
